{
    "lid_query_indices": [
        {
            "saved_idx": 0,
            "dataset_idx": 2431
        },
        {
            "saved_idx": 1,
            "dataset_idx": 350
        },
        {
            "saved_idx": 2,
            "dataset_idx": 1044
        },
        {
            "saved_idx": 3,
            "dataset_idx": 1437
        },
        {
            "saved_idx": 4,
            "dataset_idx": 2292
        },
        {
            "saved_idx": 5,
            "dataset_idx": 1498
        },
        {
            "saved_idx": 6,
            "dataset_idx": 569
        },
        {
            "saved_idx": 7,
            "dataset_idx": 840
        },
        {
            "saved_idx": 8,
            "dataset_idx": 1655
        },
        {
            "saved_idx": 9,
            "dataset_idx": 2313
        },
        {
            "saved_idx": 10,
            "dataset_idx": 3123
        },
        {
            "saved_idx": 11,
            "dataset_idx": 1752
        },
        {
            "saved_idx": 12,
            "dataset_idx": 229
        },
        {
            "saved_idx": 13,
            "dataset_idx": 2198
        },
        {
            "saved_idx": 14,
            "dataset_idx": 602
        },
        {
            "saved_idx": 15,
            "dataset_idx": 2363
        },
        {
            "saved_idx": 16,
            "dataset_idx": 1827
        },
        {
            "saved_idx": 17,
            "dataset_idx": 121
        },
        {
            "saved_idx": 18,
            "dataset_idx": 3483
        },
        {
            "saved_idx": 19,
            "dataset_idx": 2323
        },
        {
            "saved_idx": 20,
            "dataset_idx": 1146
        },
        {
            "saved_idx": 21,
            "dataset_idx": 1029
        },
        {
            "saved_idx": 22,
            "dataset_idx": 82
        },
        {
            "saved_idx": 23,
            "dataset_idx": 3456
        },
        {
            "saved_idx": 24,
            "dataset_idx": 2458
        },
        {
            "saved_idx": 25,
            "dataset_idx": 3065
        },
        {
            "saved_idx": 26,
            "dataset_idx": 1003
        },
        {
            "saved_idx": 27,
            "dataset_idx": 651
        },
        {
            "saved_idx": 28,
            "dataset_idx": 1357
        },
        {
            "saved_idx": 29,
            "dataset_idx": 335
        },
        {
            "saved_idx": 30,
            "dataset_idx": 3199
        },
        {
            "saved_idx": 31,
            "dataset_idx": 2069
        },
        {
            "saved_idx": 32,
            "dataset_idx": 2385
        },
        {
            "saved_idx": 33,
            "dataset_idx": 1974
        },
        {
            "saved_idx": 34,
            "dataset_idx": 1834
        },
        {
            "saved_idx": 35,
            "dataset_idx": 1691
        },
        {
            "saved_idx": 36,
            "dataset_idx": 14
        },
        {
            "saved_idx": 37,
            "dataset_idx": 1525
        },
        {
            "saved_idx": 38,
            "dataset_idx": 2705
        },
        {
            "saved_idx": 39,
            "dataset_idx": 996
        },
        {
            "saved_idx": 40,
            "dataset_idx": 2999
        },
        {
            "saved_idx": 41,
            "dataset_idx": 367
        },
        {
            "saved_idx": 42,
            "dataset_idx": 714
        },
        {
            "saved_idx": 43,
            "dataset_idx": 357
        },
        {
            "saved_idx": 44,
            "dataset_idx": 1789
        },
        {
            "saved_idx": 45,
            "dataset_idx": 2906
        },
        {
            "saved_idx": 46,
            "dataset_idx": 3094
        },
        {
            "saved_idx": 47,
            "dataset_idx": 1290
        },
        {
            "saved_idx": 48,
            "dataset_idx": 2378
        },
        {
            "saved_idx": 49,
            "dataset_idx": 2469
        },
        {
            "saved_idx": 50,
            "dataset_idx": 3236
        },
        {
            "saved_idx": 51,
            "dataset_idx": 1269
        },
        {
            "saved_idx": 52,
            "dataset_idx": 10
        },
        {
            "saved_idx": 53,
            "dataset_idx": 3237
        },
        {
            "saved_idx": 54,
            "dataset_idx": 2468
        },
        {
            "saved_idx": 55,
            "dataset_idx": 1698
        },
        {
            "saved_idx": 56,
            "dataset_idx": 1810
        },
        {
            "saved_idx": 57,
            "dataset_idx": 290
        },
        {
            "saved_idx": 58,
            "dataset_idx": 1025
        },
        {
            "saved_idx": 59,
            "dataset_idx": 1150
        },
        {
            "saved_idx": 60,
            "dataset_idx": 2277
        },
        {
            "saved_idx": 61,
            "dataset_idx": 3465
        },
        {
            "saved_idx": 62,
            "dataset_idx": 2868
        },
        {
            "saved_idx": 63,
            "dataset_idx": 1835
        },
        {
            "saved_idx": 64,
            "dataset_idx": 3136
        },
        {
            "saved_idx": 65,
            "dataset_idx": 2795
        },
        {
            "saved_idx": 66,
            "dataset_idx": 80
        },
        {
            "saved_idx": 67,
            "dataset_idx": 2510
        },
        {
            "saved_idx": 68,
            "dataset_idx": 1325
        },
        {
            "saved_idx": 69,
            "dataset_idx": 2943
        },
        {
            "saved_idx": 70,
            "dataset_idx": 3125
        },
        {
            "saved_idx": 71,
            "dataset_idx": 2728
        },
        {
            "saved_idx": 72,
            "dataset_idx": 2989
        },
        {
            "saved_idx": 73,
            "dataset_idx": 953
        },
        {
            "saved_idx": 74,
            "dataset_idx": 3468
        },
        {
            "saved_idx": 75,
            "dataset_idx": 818
        },
        {
            "saved_idx": 76,
            "dataset_idx": 1787
        },
        {
            "saved_idx": 77,
            "dataset_idx": 1494
        },
        {
            "saved_idx": 78,
            "dataset_idx": 1054
        },
        {
            "saved_idx": 79,
            "dataset_idx": 3219
        }
    ],
    "acc_query_indices": [
        {
            "saved_idx": 80,
            "dataset_idx": 3623
        },
        {
            "saved_idx": 81,
            "dataset_idx": 239
        },
        {
            "saved_idx": 82,
            "dataset_idx": 238
        },
        {
            "saved_idx": 83,
            "dataset_idx": 3488
        },
        {
            "saved_idx": 84,
            "dataset_idx": 2630
        },
        {
            "saved_idx": 85,
            "dataset_idx": 2807
        },
        {
            "saved_idx": 86,
            "dataset_idx": 3050
        },
        {
            "saved_idx": 87,
            "dataset_idx": 2616
        },
        {
            "saved_idx": 88,
            "dataset_idx": 547
        },
        {
            "saved_idx": 89,
            "dataset_idx": 3017
        },
        {
            "saved_idx": 90,
            "dataset_idx": 302
        },
        {
            "saved_idx": 91,
            "dataset_idx": 2612
        },
        {
            "saved_idx": 92,
            "dataset_idx": 2459
        },
        {
            "saved_idx": 93,
            "dataset_idx": 2257
        },
        {
            "saved_idx": 94,
            "dataset_idx": 44
        },
        {
            "saved_idx": 95,
            "dataset_idx": 1489
        },
        {
            "saved_idx": 96,
            "dataset_idx": 1165
        },
        {
            "saved_idx": 97,
            "dataset_idx": 3537
        },
        {
            "saved_idx": 98,
            "dataset_idx": 850
        },
        {
            "saved_idx": 99,
            "dataset_idx": 2228
        },
        {
            "saved_idx": 100,
            "dataset_idx": 2644
        },
        {
            "saved_idx": 101,
            "dataset_idx": 283
        },
        {
            "saved_idx": 102,
            "dataset_idx": 2338
        },
        {
            "saved_idx": 103,
            "dataset_idx": 566
        },
        {
            "saved_idx": 104,
            "dataset_idx": 2153
        },
        {
            "saved_idx": 105,
            "dataset_idx": 1793
        },
        {
            "saved_idx": 106,
            "dataset_idx": 2317
        },
        {
            "saved_idx": 107,
            "dataset_idx": 734
        },
        {
            "saved_idx": 108,
            "dataset_idx": 3581
        },
        {
            "saved_idx": 109,
            "dataset_idx": 36
        },
        {
            "saved_idx": 110,
            "dataset_idx": 2873
        },
        {
            "saved_idx": 111,
            "dataset_idx": 1439
        },
        {
            "saved_idx": 112,
            "dataset_idx": 1565
        },
        {
            "saved_idx": 113,
            "dataset_idx": 1996
        },
        {
            "saved_idx": 114,
            "dataset_idx": 1355
        },
        {
            "saved_idx": 115,
            "dataset_idx": 3257
        },
        {
            "saved_idx": 116,
            "dataset_idx": 2683
        },
        {
            "saved_idx": 117,
            "dataset_idx": 3521
        },
        {
            "saved_idx": 118,
            "dataset_idx": 1884
        },
        {
            "saved_idx": 119,
            "dataset_idx": 1582
        },
        {
            "saved_idx": 120,
            "dataset_idx": 2061
        },
        {
            "saved_idx": 121,
            "dataset_idx": 1047
        },
        {
            "saved_idx": 122,
            "dataset_idx": 749
        },
        {
            "saved_idx": 123,
            "dataset_idx": 2256
        },
        {
            "saved_idx": 124,
            "dataset_idx": 1642
        },
        {
            "saved_idx": 125,
            "dataset_idx": 555
        },
        {
            "saved_idx": 126,
            "dataset_idx": 42
        },
        {
            "saved_idx": 127,
            "dataset_idx": 2223
        },
        {
            "saved_idx": 128,
            "dataset_idx": 2538
        },
        {
            "saved_idx": 129,
            "dataset_idx": 318
        },
        {
            "saved_idx": 130,
            "dataset_idx": 2112
        },
        {
            "saved_idx": 131,
            "dataset_idx": 3594
        },
        {
            "saved_idx": 132,
            "dataset_idx": 1935
        },
        {
            "saved_idx": 133,
            "dataset_idx": 1159
        },
        {
            "saved_idx": 134,
            "dataset_idx": 1324
        },
        {
            "saved_idx": 135,
            "dataset_idx": 2650
        },
        {
            "saved_idx": 136,
            "dataset_idx": 3168
        },
        {
            "saved_idx": 137,
            "dataset_idx": 939
        },
        {
            "saved_idx": 138,
            "dataset_idx": 1767
        },
        {
            "saved_idx": 139,
            "dataset_idx": 2872
        },
        {
            "saved_idx": 140,
            "dataset_idx": 630
        },
        {
            "saved_idx": 141,
            "dataset_idx": 385
        },
        {
            "saved_idx": 142,
            "dataset_idx": 868
        },
        {
            "saved_idx": 143,
            "dataset_idx": 1288
        },
        {
            "saved_idx": 144,
            "dataset_idx": 3122
        },
        {
            "saved_idx": 145,
            "dataset_idx": 236
        },
        {
            "saved_idx": 146,
            "dataset_idx": 601
        },
        {
            "saved_idx": 147,
            "dataset_idx": 16
        },
        {
            "saved_idx": 148,
            "dataset_idx": 372
        },
        {
            "saved_idx": 149,
            "dataset_idx": 1205
        },
        {
            "saved_idx": 150,
            "dataset_idx": 724
        },
        {
            "saved_idx": 151,
            "dataset_idx": 1815
        },
        {
            "saved_idx": 152,
            "dataset_idx": 3378
        },
        {
            "saved_idx": 153,
            "dataset_idx": 2886
        },
        {
            "saved_idx": 154,
            "dataset_idx": 466
        },
        {
            "saved_idx": 155,
            "dataset_idx": 2760
        },
        {
            "saved_idx": 156,
            "dataset_idx": 1507
        },
        {
            "saved_idx": 157,
            "dataset_idx": 1451
        },
        {
            "saved_idx": 158,
            "dataset_idx": 3027
        },
        {
            "saved_idx": 159,
            "dataset_idx": 2821
        }
    ],
    "demonstration_indices": [
        [
            {
                "saved_idx": 160,
                "dataset_idx": 143
            },
            {
                "saved_idx": 161,
                "dataset_idx": 3364
            },
            {
                "saved_idx": 162,
                "dataset_idx": 3225
            },
            {
                "saved_idx": 163,
                "dataset_idx": 192
            },
            {
                "saved_idx": 164,
                "dataset_idx": 844
            }
        ],
        [
            {
                "saved_idx": 165,
                "dataset_idx": 2029
            },
            {
                "saved_idx": 166,
                "dataset_idx": 1232
            },
            {
                "saved_idx": 167,
                "dataset_idx": 2830
            },
            {
                "saved_idx": 168,
                "dataset_idx": 889
            },
            {
                "saved_idx": 169,
                "dataset_idx": 1115
            }
        ],
        [
            {
                "saved_idx": 170,
                "dataset_idx": 3058
            },
            {
                "saved_idx": 171,
                "dataset_idx": 1872
            },
            {
                "saved_idx": 172,
                "dataset_idx": 144
            },
            {
                "saved_idx": 173,
                "dataset_idx": 3539
            },
            {
                "saved_idx": 174,
                "dataset_idx": 3416
            }
        ],
        [
            {
                "saved_idx": 175,
                "dataset_idx": 3458
            },
            {
                "saved_idx": 176,
                "dataset_idx": 433
            },
            {
                "saved_idx": 177,
                "dataset_idx": 1825
            },
            {
                "saved_idx": 178,
                "dataset_idx": 1187
            },
            {
                "saved_idx": 179,
                "dataset_idx": 1388
            }
        ],
        [
            {
                "saved_idx": 180,
                "dataset_idx": 2962
            },
            {
                "saved_idx": 181,
                "dataset_idx": 3342
            },
            {
                "saved_idx": 182,
                "dataset_idx": 886
            },
            {
                "saved_idx": 183,
                "dataset_idx": 2729
            },
            {
                "saved_idx": 184,
                "dataset_idx": 1491
            }
        ],
        [
            {
                "saved_idx": 185,
                "dataset_idx": 3160
            },
            {
                "saved_idx": 186,
                "dataset_idx": 1755
            },
            {
                "saved_idx": 187,
                "dataset_idx": 3326
            },
            {
                "saved_idx": 188,
                "dataset_idx": 3311
            },
            {
                "saved_idx": 189,
                "dataset_idx": 2004
            }
        ],
        [
            {
                "saved_idx": 190,
                "dataset_idx": 107
            },
            {
                "saved_idx": 191,
                "dataset_idx": 2765
            },
            {
                "saved_idx": 192,
                "dataset_idx": 639
            },
            {
                "saved_idx": 193,
                "dataset_idx": 1878
            },
            {
                "saved_idx": 194,
                "dataset_idx": 2297
            }
        ],
        [
            {
                "saved_idx": 195,
                "dataset_idx": 2375
            },
            {
                "saved_idx": 196,
                "dataset_idx": 704
            },
            {
                "saved_idx": 197,
                "dataset_idx": 1937
            },
            {
                "saved_idx": 198,
                "dataset_idx": 983
            },
            {
                "saved_idx": 199,
                "dataset_idx": 3082
            }
        ],
        [
            {
                "saved_idx": 200,
                "dataset_idx": 2267
            },
            {
                "saved_idx": 201,
                "dataset_idx": 624
            },
            {
                "saved_idx": 202,
                "dataset_idx": 117
            },
            {
                "saved_idx": 203,
                "dataset_idx": 1753
            },
            {
                "saved_idx": 204,
                "dataset_idx": 1343
            }
        ],
        [
            {
                "saved_idx": 205,
                "dataset_idx": 535
            },
            {
                "saved_idx": 206,
                "dataset_idx": 632
            },
            {
                "saved_idx": 207,
                "dataset_idx": 2373
            },
            {
                "saved_idx": 208,
                "dataset_idx": 2779
            },
            {
                "saved_idx": 209,
                "dataset_idx": 3276
            }
        ],
        [
            {
                "saved_idx": 210,
                "dataset_idx": 3374
            },
            {
                "saved_idx": 211,
                "dataset_idx": 3292
            },
            {
                "saved_idx": 212,
                "dataset_idx": 460
            },
            {
                "saved_idx": 213,
                "dataset_idx": 1665
            },
            {
                "saved_idx": 214,
                "dataset_idx": 3624
            }
        ],
        [
            {
                "saved_idx": 215,
                "dataset_idx": 3524
            },
            {
                "saved_idx": 216,
                "dataset_idx": 1291
            },
            {
                "saved_idx": 217,
                "dataset_idx": 3384
            },
            {
                "saved_idx": 218,
                "dataset_idx": 336
            },
            {
                "saved_idx": 219,
                "dataset_idx": 1122
            }
        ],
        [
            {
                "saved_idx": 220,
                "dataset_idx": 1774
            },
            {
                "saved_idx": 221,
                "dataset_idx": 2633
            },
            {
                "saved_idx": 222,
                "dataset_idx": 48
            },
            {
                "saved_idx": 223,
                "dataset_idx": 1076
            },
            {
                "saved_idx": 224,
                "dataset_idx": 3542
            }
        ],
        [
            {
                "saved_idx": 225,
                "dataset_idx": 660
            },
            {
                "saved_idx": 226,
                "dataset_idx": 1785
            },
            {
                "saved_idx": 227,
                "dataset_idx": 2013
            },
            {
                "saved_idx": 228,
                "dataset_idx": 1455
            },
            {
                "saved_idx": 229,
                "dataset_idx": 3590
            }
        ],
        [
            {
                "saved_idx": 230,
                "dataset_idx": 170
            },
            {
                "saved_idx": 231,
                "dataset_idx": 1637
            },
            {
                "saved_idx": 232,
                "dataset_idx": 2208
            },
            {
                "saved_idx": 233,
                "dataset_idx": 2552
            },
            {
                "saved_idx": 234,
                "dataset_idx": 3162
            }
        ],
        [
            {
                "saved_idx": 235,
                "dataset_idx": 1467
            },
            {
                "saved_idx": 236,
                "dataset_idx": 3026
            },
            {
                "saved_idx": 237,
                "dataset_idx": 8
            },
            {
                "saved_idx": 238,
                "dataset_idx": 3263
            },
            {
                "saved_idx": 239,
                "dataset_idx": 2419
            }
        ],
        [
            {
                "saved_idx": 240,
                "dataset_idx": 1703
            },
            {
                "saved_idx": 241,
                "dataset_idx": 2254
            },
            {
                "saved_idx": 242,
                "dataset_idx": 2696
            },
            {
                "saved_idx": 243,
                "dataset_idx": 2586
            },
            {
                "saved_idx": 244,
                "dataset_idx": 650
            }
        ],
        [
            {
                "saved_idx": 245,
                "dataset_idx": 3443
            },
            {
                "saved_idx": 246,
                "dataset_idx": 1252
            },
            {
                "saved_idx": 247,
                "dataset_idx": 105
            },
            {
                "saved_idx": 248,
                "dataset_idx": 1632
            },
            {
                "saved_idx": 249,
                "dataset_idx": 2861
            }
        ],
        [
            {
                "saved_idx": 250,
                "dataset_idx": 496
            },
            {
                "saved_idx": 251,
                "dataset_idx": 1335
            },
            {
                "saved_idx": 252,
                "dataset_idx": 13
            },
            {
                "saved_idx": 253,
                "dataset_idx": 2157
            },
            {
                "saved_idx": 254,
                "dataset_idx": 2894
            }
        ],
        [
            {
                "saved_idx": 255,
                "dataset_idx": 621
            },
            {
                "saved_idx": 256,
                "dataset_idx": 3172
            },
            {
                "saved_idx": 257,
                "dataset_idx": 2972
            },
            {
                "saved_idx": 258,
                "dataset_idx": 725
            },
            {
                "saved_idx": 259,
                "dataset_idx": 1168
            }
        ],
        [
            {
                "saved_idx": 260,
                "dataset_idx": 745
            },
            {
                "saved_idx": 261,
                "dataset_idx": 705
            },
            {
                "saved_idx": 262,
                "dataset_idx": 2988
            },
            {
                "saved_idx": 263,
                "dataset_idx": 294
            },
            {
                "saved_idx": 264,
                "dataset_idx": 1880
            }
        ],
        [
            {
                "saved_idx": 265,
                "dataset_idx": 1603
            },
            {
                "saved_idx": 266,
                "dataset_idx": 2463
            },
            {
                "saved_idx": 267,
                "dataset_idx": 836
            },
            {
                "saved_idx": 268,
                "dataset_idx": 3578
            },
            {
                "saved_idx": 269,
                "dataset_idx": 267
            }
        ],
        [
            {
                "saved_idx": 270,
                "dataset_idx": 2136
            },
            {
                "saved_idx": 271,
                "dataset_idx": 1846
            },
            {
                "saved_idx": 272,
                "dataset_idx": 1991
            },
            {
                "saved_idx": 273,
                "dataset_idx": 1587
            },
            {
                "saved_idx": 274,
                "dataset_idx": 390
            }
        ],
        [
            {
                "saved_idx": 275,
                "dataset_idx": 260
            },
            {
                "saved_idx": 276,
                "dataset_idx": 937
            },
            {
                "saved_idx": 277,
                "dataset_idx": 3250
            },
            {
                "saved_idx": 278,
                "dataset_idx": 1286
            },
            {
                "saved_idx": 279,
                "dataset_idx": 2684
            }
        ],
        [
            {
                "saved_idx": 280,
                "dataset_idx": 2743
            },
            {
                "saved_idx": 281,
                "dataset_idx": 1499
            },
            {
                "saved_idx": 282,
                "dataset_idx": 841
            },
            {
                "saved_idx": 283,
                "dataset_idx": 1748
            },
            {
                "saved_idx": 284,
                "dataset_idx": 549
            }
        ],
        [
            {
                "saved_idx": 285,
                "dataset_idx": 2665
            },
            {
                "saved_idx": 286,
                "dataset_idx": 2659
            },
            {
                "saved_idx": 287,
                "dataset_idx": 781
            },
            {
                "saved_idx": 288,
                "dataset_idx": 1744
            },
            {
                "saved_idx": 289,
                "dataset_idx": 141
            }
        ],
        [
            {
                "saved_idx": 290,
                "dataset_idx": 1048
            },
            {
                "saved_idx": 291,
                "dataset_idx": 3164
            },
            {
                "saved_idx": 292,
                "dataset_idx": 2804
            },
            {
                "saved_idx": 293,
                "dataset_idx": 669
            },
            {
                "saved_idx": 294,
                "dataset_idx": 2357
            }
        ],
        [
            {
                "saved_idx": 295,
                "dataset_idx": 56
            },
            {
                "saved_idx": 296,
                "dataset_idx": 3059
            },
            {
                "saved_idx": 297,
                "dataset_idx": 2963
            },
            {
                "saved_idx": 298,
                "dataset_idx": 1121
            },
            {
                "saved_idx": 299,
                "dataset_idx": 3035
            }
        ],
        [
            {
                "saved_idx": 300,
                "dataset_idx": 1524
            },
            {
                "saved_idx": 301,
                "dataset_idx": 1531
            },
            {
                "saved_idx": 302,
                "dataset_idx": 2471
            },
            {
                "saved_idx": 303,
                "dataset_idx": 2608
            },
            {
                "saved_idx": 304,
                "dataset_idx": 3023
            }
        ],
        [
            {
                "saved_idx": 305,
                "dataset_idx": 418
            },
            {
                "saved_idx": 306,
                "dataset_idx": 75
            },
            {
                "saved_idx": 307,
                "dataset_idx": 2777
            },
            {
                "saved_idx": 308,
                "dataset_idx": 3455
            },
            {
                "saved_idx": 309,
                "dataset_idx": 2109
            }
        ],
        [
            {
                "saved_idx": 310,
                "dataset_idx": 1975
            },
            {
                "saved_idx": 311,
                "dataset_idx": 2245
            },
            {
                "saved_idx": 312,
                "dataset_idx": 2500
            },
            {
                "saved_idx": 313,
                "dataset_idx": 1759
            },
            {
                "saved_idx": 314,
                "dataset_idx": 1135
            }
        ],
        [
            {
                "saved_idx": 315,
                "dataset_idx": 3149
            },
            {
                "saved_idx": 316,
                "dataset_idx": 1666
            },
            {
                "saved_idx": 317,
                "dataset_idx": 1404
            },
            {
                "saved_idx": 318,
                "dataset_idx": 162
            },
            {
                "saved_idx": 319,
                "dataset_idx": 2405
            }
        ],
        [
            {
                "saved_idx": 320,
                "dataset_idx": 2740
            },
            {
                "saved_idx": 321,
                "dataset_idx": 3197
            },
            {
                "saved_idx": 322,
                "dataset_idx": 1015
            },
            {
                "saved_idx": 323,
                "dataset_idx": 2580
            },
            {
                "saved_idx": 324,
                "dataset_idx": 4
            }
        ],
        [
            {
                "saved_idx": 325,
                "dataset_idx": 3261
            },
            {
                "saved_idx": 326,
                "dataset_idx": 321
            },
            {
                "saved_idx": 327,
                "dataset_idx": 1726
            },
            {
                "saved_idx": 328,
                "dataset_idx": 2523
            },
            {
                "saved_idx": 329,
                "dataset_idx": 2401
            }
        ],
        [
            {
                "saved_idx": 330,
                "dataset_idx": 864
            },
            {
                "saved_idx": 331,
                "dataset_idx": 69
            },
            {
                "saved_idx": 332,
                "dataset_idx": 128
            },
            {
                "saved_idx": 333,
                "dataset_idx": 2916
            },
            {
                "saved_idx": 334,
                "dataset_idx": 157
            }
        ],
        [
            {
                "saved_idx": 335,
                "dataset_idx": 2605
            },
            {
                "saved_idx": 336,
                "dataset_idx": 2187
            },
            {
                "saved_idx": 337,
                "dataset_idx": 483
            },
            {
                "saved_idx": 338,
                "dataset_idx": 3619
            },
            {
                "saved_idx": 339,
                "dataset_idx": 635
            }
        ],
        [
            {
                "saved_idx": 340,
                "dataset_idx": 3482
            },
            {
                "saved_idx": 341,
                "dataset_idx": 3592
            },
            {
                "saved_idx": 342,
                "dataset_idx": 3591
            },
            {
                "saved_idx": 343,
                "dataset_idx": 1961
            },
            {
                "saved_idx": 344,
                "dataset_idx": 1322
            }
        ],
        [
            {
                "saved_idx": 345,
                "dataset_idx": 1578
            },
            {
                "saved_idx": 346,
                "dataset_idx": 956
            },
            {
                "saved_idx": 347,
                "dataset_idx": 47
            },
            {
                "saved_idx": 348,
                "dataset_idx": 1414
            },
            {
                "saved_idx": 349,
                "dataset_idx": 1123
            }
        ],
        [
            {
                "saved_idx": 350,
                "dataset_idx": 1098
            },
            {
                "saved_idx": 351,
                "dataset_idx": 1514
            },
            {
                "saved_idx": 352,
                "dataset_idx": 2895
            },
            {
                "saved_idx": 353,
                "dataset_idx": 15
            },
            {
                "saved_idx": 354,
                "dataset_idx": 2279
            }
        ],
        [
            {
                "saved_idx": 355,
                "dataset_idx": 656
            },
            {
                "saved_idx": 356,
                "dataset_idx": 3144
            },
            {
                "saved_idx": 357,
                "dataset_idx": 1317
            },
            {
                "saved_idx": 358,
                "dataset_idx": 2093
            },
            {
                "saved_idx": 359,
                "dataset_idx": 1102
            }
        ],
        [
            {
                "saved_idx": 360,
                "dataset_idx": 3308
            },
            {
                "saved_idx": 361,
                "dataset_idx": 741
            },
            {
                "saved_idx": 362,
                "dataset_idx": 237
            },
            {
                "saved_idx": 363,
                "dataset_idx": 2537
            },
            {
                "saved_idx": 364,
                "dataset_idx": 2178
            }
        ],
        [
            {
                "saved_idx": 365,
                "dataset_idx": 2379
            },
            {
                "saved_idx": 366,
                "dataset_idx": 2078
            },
            {
                "saved_idx": 367,
                "dataset_idx": 1190
            },
            {
                "saved_idx": 368,
                "dataset_idx": 244
            },
            {
                "saved_idx": 369,
                "dataset_idx": 320
            }
        ],
        [
            {
                "saved_idx": 370,
                "dataset_idx": 924
            },
            {
                "saved_idx": 371,
                "dataset_idx": 426
            },
            {
                "saved_idx": 372,
                "dataset_idx": 2876
            },
            {
                "saved_idx": 373,
                "dataset_idx": 528
            },
            {
                "saved_idx": 374,
                "dataset_idx": 1375
            }
        ],
        [
            {
                "saved_idx": 375,
                "dataset_idx": 746
            },
            {
                "saved_idx": 376,
                "dataset_idx": 722
            },
            {
                "saved_idx": 377,
                "dataset_idx": 2832
            },
            {
                "saved_idx": 378,
                "dataset_idx": 2202
            },
            {
                "saved_idx": 379,
                "dataset_idx": 845
            }
        ],
        [
            {
                "saved_idx": 380,
                "dataset_idx": 3193
            },
            {
                "saved_idx": 381,
                "dataset_idx": 3115
            },
            {
                "saved_idx": 382,
                "dataset_idx": 3569
            },
            {
                "saved_idx": 383,
                "dataset_idx": 591
            },
            {
                "saved_idx": 384,
                "dataset_idx": 1509
            }
        ],
        [
            {
                "saved_idx": 385,
                "dataset_idx": 1725
            },
            {
                "saved_idx": 386,
                "dataset_idx": 215
            },
            {
                "saved_idx": 387,
                "dataset_idx": 2514
            },
            {
                "saved_idx": 388,
                "dataset_idx": 2561
            },
            {
                "saved_idx": 389,
                "dataset_idx": 905
            }
        ],
        [
            {
                "saved_idx": 390,
                "dataset_idx": 1120
            },
            {
                "saved_idx": 391,
                "dataset_idx": 3343
            },
            {
                "saved_idx": 392,
                "dataset_idx": 2355
            },
            {
                "saved_idx": 393,
                "dataset_idx": 3025
            },
            {
                "saved_idx": 394,
                "dataset_idx": 2002
            }
        ],
        [
            {
                "saved_idx": 395,
                "dataset_idx": 3203
            },
            {
                "saved_idx": 396,
                "dataset_idx": 3448
            },
            {
                "saved_idx": 397,
                "dataset_idx": 1064
            },
            {
                "saved_idx": 398,
                "dataset_idx": 2442
            },
            {
                "saved_idx": 399,
                "dataset_idx": 173
            }
        ],
        [
            {
                "saved_idx": 400,
                "dataset_idx": 1310
            },
            {
                "saved_idx": 401,
                "dataset_idx": 969
            },
            {
                "saved_idx": 402,
                "dataset_idx": 1807
            },
            {
                "saved_idx": 403,
                "dataset_idx": 2155
            },
            {
                "saved_idx": 404,
                "dataset_idx": 713
            }
        ],
        [
            {
                "saved_idx": 405,
                "dataset_idx": 2414
            },
            {
                "saved_idx": 406,
                "dataset_idx": 497
            },
            {
                "saved_idx": 407,
                "dataset_idx": 2235
            },
            {
                "saved_idx": 408,
                "dataset_idx": 727
            },
            {
                "saved_idx": 409,
                "dataset_idx": 1420
            }
        ],
        [
            {
                "saved_idx": 410,
                "dataset_idx": 1862
            },
            {
                "saved_idx": 411,
                "dataset_idx": 161
            },
            {
                "saved_idx": 412,
                "dataset_idx": 2299
            },
            {
                "saved_idx": 413,
                "dataset_idx": 678
            },
            {
                "saved_idx": 414,
                "dataset_idx": 1930
            }
        ],
        [
            {
                "saved_idx": 415,
                "dataset_idx": 2939
            },
            {
                "saved_idx": 416,
                "dataset_idx": 3081
            },
            {
                "saved_idx": 417,
                "dataset_idx": 1505
            },
            {
                "saved_idx": 418,
                "dataset_idx": 1553
            },
            {
                "saved_idx": 419,
                "dataset_idx": 2986
            }
        ],
        [
            {
                "saved_idx": 420,
                "dataset_idx": 1340
            },
            {
                "saved_idx": 421,
                "dataset_idx": 1341
            },
            {
                "saved_idx": 422,
                "dataset_idx": 1613
            },
            {
                "saved_idx": 423,
                "dataset_idx": 2852
            },
            {
                "saved_idx": 424,
                "dataset_idx": 2491
            }
        ],
        [
            {
                "saved_idx": 425,
                "dataset_idx": 1914
            },
            {
                "saved_idx": 426,
                "dataset_idx": 29
            },
            {
                "saved_idx": 427,
                "dataset_idx": 3446
            },
            {
                "saved_idx": 428,
                "dataset_idx": 1534
            },
            {
                "saved_idx": 429,
                "dataset_idx": 2536
            }
        ],
        [
            {
                "saved_idx": 430,
                "dataset_idx": 584
            },
            {
                "saved_idx": 431,
                "dataset_idx": 2408
            },
            {
                "saved_idx": 432,
                "dataset_idx": 3037
            },
            {
                "saved_idx": 433,
                "dataset_idx": 1408
            },
            {
                "saved_idx": 434,
                "dataset_idx": 2556
            }
        ],
        [
            {
                "saved_idx": 435,
                "dataset_idx": 1328
            },
            {
                "saved_idx": 436,
                "dataset_idx": 2121
            },
            {
                "saved_idx": 437,
                "dataset_idx": 2949
            },
            {
                "saved_idx": 438,
                "dataset_idx": 2828
            },
            {
                "saved_idx": 439,
                "dataset_idx": 3334
            }
        ],
        [
            {
                "saved_idx": 440,
                "dataset_idx": 1714
            },
            {
                "saved_idx": 441,
                "dataset_idx": 1209
            },
            {
                "saved_idx": 442,
                "dataset_idx": 0
            },
            {
                "saved_idx": 443,
                "dataset_idx": 2456
            },
            {
                "saved_idx": 444,
                "dataset_idx": 2866
            }
        ],
        [
            {
                "saved_idx": 445,
                "dataset_idx": 3330
            },
            {
                "saved_idx": 446,
                "dataset_idx": 39
            },
            {
                "saved_idx": 447,
                "dataset_idx": 1039
            },
            {
                "saved_idx": 448,
                "dataset_idx": 2164
            },
            {
                "saved_idx": 449,
                "dataset_idx": 1230
            }
        ],
        [
            {
                "saved_idx": 450,
                "dataset_idx": 682
            },
            {
                "saved_idx": 451,
                "dataset_idx": 6
            },
            {
                "saved_idx": 452,
                "dataset_idx": 1593
            },
            {
                "saved_idx": 453,
                "dataset_idx": 622
            },
            {
                "saved_idx": 454,
                "dataset_idx": 3380
            }
        ],
        [
            {
                "saved_idx": 455,
                "dataset_idx": 1504
            },
            {
                "saved_idx": 456,
                "dataset_idx": 246
            },
            {
                "saved_idx": 457,
                "dataset_idx": 706
            },
            {
                "saved_idx": 458,
                "dataset_idx": 942
            },
            {
                "saved_idx": 459,
                "dataset_idx": 3367
            }
        ]
    ]
}